LICENSE
README.md
setup.cfg
setup.py
aheui/__init__.py
aheui/_argparse.py
aheui/_compat.py
aheui/aheui.py
aheui/compile.py
aheui/const.py
aheui/option.py
aheui/version.py
aheui/warning.py
aheui.egg-info/PKG-INFO
aheui.egg-info/SOURCES.txt
aheui.egg-info/dependency_links.txt
aheui.egg-info/requires.txt
aheui.egg-info/top_level.txt
aheui/int/__init__.py
aheui/int/bigint.py
aheui/int/smallint.py
bin/aheui
bin/aheui-py
bin/ahsembler
tests/test_compile.py