Metadata-Version: 2.1
Name: aheui
Version: 1.2.5
Summary: Aheui compiler & assembler toolkit.
Home-page: https://github.com/aheui/rpaheui
Author: Jeong YunWon
Author-email: aheui@youknowone.org
License: UNKNOWN
Platform: UNKNOWN
Classifier: Intended Audience :: Developers
Classifier: Operating System :: OS Independent
Classifier: Programming Language :: Python
Classifier: Programming Language :: Python :: 2
Classifier: Programming Language :: Python :: 2.7
Classifier: Programming Language :: Python :: 3
Classifier: Programming Language :: Python :: 3.12
Provides-Extra: tests
